rend/conf.py
rend/exc.py
rend/scripts.py
rend/version.py
rend/output/json_out.py
rend/output/nested.py
rend/output/pretty.py
rend/output/raw.py
rend/output/yaml_out.py
rend/output/contracts/init.py
rend/rend/init.py
rend/rend/jinja.py
rend/rend/json_file.py
rend/rend/k8crd_file.py
rend/rend/replacements.py
rend/rend/toml_file.py
rend/rend/yaml_file.py
rend/rend/contracts/init.py
rend-7.0.2.dist-info/LICENSE
rend-7.0.2.dist-info/METADATA
rend-7.0.2.dist-info/WHEEL
rend-7.0.2.dist-info/entry_points.txt
rend-7.0.2.dist-info/top_level.txt
rend-7.0.2.dist-info/RECORD
